{
    "1": {
        "media": "text",
        "cards": [
            {
                "sideA": "וַלַד",
                "sideB": "ילד"
            },
            {
                "sideA": "בִּנְת",
                "sideB": "ילדה"
            },
            {
                "sideA": "סֻאַאל",
                "sideB": "שאלה"
            },
            {
                "sideA": "מֻשְכִּלֵה",
                "sideB": "בעיה"
            },
            {
                "sideA": "סַיַّארַה",
                "sideB": "מכונית"
            },
            {
                "sideA": "צוּרַה",
                "sideB": "תמונה"
            }
        ]
    },
    "2": {
        "media": "audio",
        "cards": [
            {
                "sideA": "וַלַד",
                "sideB": "https://madrasa-voice.s3.eu-west-2.amazonaws.com/Med/VocabTableMed/les1/2.28.wav"
            },
            {
                "sideA": "בִּנְת",
                "sideB": "https://madrasa-voice.s3.eu-west-2.amazonaws.com/Med/VocabTableMed/les1/2.29.wav"
            },
            {
                "sideA": "סֻאַאל",
                "sideB": "https://madrasa-voice.s3.eu-west-2.amazonaws.com/Med/VocabTableMed/les1/2.18.wav"
            },
            {
                "sideA": "מֻשְכִּלֵה",
                "sideB": "https://madrasa-voice.s3.eu-west-2.amazonaws.com/Female/Nagham+(234).mp3"
            },
            {
                "sideA": "סַיַّארַה",
                "sideB": "https://madrasa-voice.s3.eu-west-2.amazonaws.com/Female/Nagham+(240).mp3"
            },
            {
                "sideA": "צוּרַה",
                "sideB": "https://madrasa-voice.s3.eu-west-2.amazonaws.com/Female/Nagham+(246).mp3"
            }
        ]
    },
    "3": {
        "media": "image",
        "cards": [
            {
                "sideA": "וַלַד",
                "sideB": "https://blackwhite.pictures/media/XL/0905/person-people-play-boy-male-portrait-846.jpg"
            },
            {
                "sideA": "בִּנְת",
                "sideB": "https://upload.wikimedia.org/wikipedia/commons/thumb/c/ce/Small_Nepali_Girl.jpg/640px-Small_Nepali_Girl.jpg"
            },
            {
                "sideA": "סֻאַאל",
                "sideB": "https://upload.wikimedia.org/wikipedia/commons/thumb/3/35/Orange_question_mark.svg/768px-Orange_question_mark.svg.png"
            },
            {
                "sideA": "מֻשְכִּלֵה",
                "sideB": "https://upload.wikimedia.org/wikipedia/commons/thumb/0/08/Problem_Solving_-_Concept_Illustration.jpg/640px-Problem_Solving_-_Concept_Illustration.jpg"
            },
            {
                "sideA": "סַיַّארַה",
                "sideB": "https://upload.wikimedia.org/wikipedia/commons/thumb/3/3d/Electric_car_BYD_E2_White_Front.jpg/640px-Electric_car_BYD_E2_White_Front.jpg"
            },
            {
                "sideA": "צוּרַה",
                "sideB": "https://upload.wikimedia.org/wikipedia/commons/thumb/9/99/Framed_wall_art_%28Unsplash%29.jpg/640px-Framed_wall_art_%28Unsplash%29.jpg"
            }
        ]
    }
}